aksharify/__init__.py
aksharify/aksharify.py
aksharify-2.7.13.dist-info/METADATA
aksharify-2.7.13.dist-info/WHEEL
aksharify-2.7.13.dist-info/RECORD
