Metadata-Version: 2.1
Name: aksharify
Version: 2.7.13
Summary: Python Ascii + Emoji Art Module
Home-page: https://primepatel.github.io/aksharify-docs/
License: MIT
Keywords: Ascii Art,Emoji Art,Prime Patel,primepatel
Author: Prime Patel
Author-email: primespatel@gmail.com
Requires-Python: >=3.10,<4.0
Classifier: License :: OSI Approved :: MIT License
Classifier: Operating System :: OS Independent
Classifier: Programming Language :: Python :: 3
Classifier: Programming Language :: Python :: 3.10
Classifier: Programming Language :: Python :: 3.11
Classifier: Programming Language :: Python :: 3.6
Classifier: Programming Language :: Python :: 3.7
Classifier: Programming Language :: Python :: 3.8
Classifier: Programming Language :: Python :: 3.9
Requires-Dist: pillow (>=8.4.0,<9.0.0)
Requires-Dist: requests (>=2.27.1,<3.0.0)
Project-URL: Repository, https://github.com/primepatel/aksharify
